{
  "code": 200,
  "msg": "处理成功！",
  "data": {
    "id": "17089797243798047",
    "apiCode": "A12",
    "apiNameEn": "AirIntlReShopOrder",
    "apiNameCn": "国际客票变更搜索(订单)",
    "introduce": "国际客票变更搜索(订单)AirIntlReShopOrder服务为用户提供了带订单查询国际客票变更费等航班信息功能的服务。",
    "business": "国际客票变更搜索（订单）",
    "functions": "支持根据航段信息，票号，查询日期来查询国际客票变更费等航班信息；相比较非订单接口，添加了对订单号的验证和订单号和票号的匹配验证。",
    "requestSchema": "[{\"name\":\"TRR_VoluntaryReshopRQ\",\"type\":\"object\",\"quantity\":\"1\",\"default\":\"\",\"description\":\"\",\"children\":[{\"name\":\"BookingOrderID\",\"type\":\"string\",\"quantity\":\"1\",\"default\":\"\",\"description\":\"订单号：1.此处填入IBE+预订订单号，如未在IBE+生成过预订单，请先通过订单同步接口导入线下商家订单 2.该订单号状态须是出票完成\",\"children\":[]},{\"name\":\"TicketInfo\",\"type\":\"object\",\"quantity\":\"1\",\"default\":\"\",\"description\":\"旅客信息\",\"children\":[{\"name\":\"TicketNo\",\"type\":\"object\",\"quantity\":\"1\",\"default\":\"\",\"description\":\"票号：13位票号或14位票号\",\"children\":[]},{\"name\":\"PassengerName\",\"type\":\"object\",\"quantity\":\"1\",\"default\":\"\",\"description\":\"\",\"children\":[]},{\"name\":\"ValidatingCarrier\",\"type\":\"object\",\"quantity\":\"1\",\"default\":\"\",\"description\":\"航空公司（承运人）两字码\",\"children\":[]}]},{\"name\":\"POS\",\"type\":\"object\",\"quantity\":\"1\",\"default\":\"\",\"description\":\"\",\"children\":[{\"name\":\"HostCode\",\"type\":\"object\",\"quantity\":\"1\",\"default\":\"\",\"description\":\"CRS时是1E ICS时是航空公司两字代码\",\"children\":[]},{\"name\":\"TicketingCity\",\"type\":\"object\",\"quantity\":\"1\",\"default\":\"\",\"description\":\"\",\"children\":[]},{\"name\":\"DepartmentCode\",\"type\":\"object\",\"quantity\":\"1\",\"default\":\"   \",\"description\":\"CRS 当是AGENT 9或者是USER GROUP 17且在PEK099时显示TST，否则是3个空格。\\n\\t\\t\\t\\t\\t\\tICS 当是AGENT 9或者是USER GROUP\\n\\t\\t\\t\\t\\t\\t17且在PEK099时显示TST，否则是C+航空公司代码。\",\"children\":[]},{\"name\":\"OfficeCode\",\"type\":\"object\",\"quantity\":\"1\",\"default\":\"\",\"description\":\"变更操作OFFICE\",\"children\":[]},{\"name\":\"IataCode\",\"type\":\"object\",\"quantity\":\"1\",\"default\":\"\",\"description\":\"变更操作office的IATA NO\",\"children\":[]}]},{\"name\":\"Segments\",\"type\":\"object\",\"quantity\":\"1\",\"default\":\"\",\"description\":\"原行程的航段信 息：已飞航班和 地面段可以 不 填 写 到 Segment\",\"children\":[{\"name\":\"Segment\",\"type\":\"object\",\"quantity\":\"0..16\",\"default\":\"\",\"description\":\"所有未飞航班的 航班信息\",\"children\":[{\"name\":\"FlightId\",\"type\":\"object\",\"quantity\":\"1\",\"default\":\"\",\"description\":\"航班的唯一编号,建议为两位数字\",\"children\":[]},{\"name\":\"MarketingCarrier\",\"type\":\"object\",\"quantity\":\"1\",\"default\":\"\",\"description\":\"航空公司（承运人）两字码\",\"children\":[]},{\"name\":\"FlightNo\",\"type\":\"object\",\"quantity\":\"1\",\"default\":\"\",\"description\":\"航班号 1、正常航班：填写航班号 2、OPEN航班：填写“OPEN”\",\"children\":[]},{\"name\":\"CabinCode\",\"type\":\"object\",\"quantity\":\"1\",\"default\":\"\",\"description\":\"舱位等级\",\"children\":[]},{\"name\":\"OperatingCarrier\",\"type\":\"object\",\"quantity\":\"0..n\",\"default\":\"\",\"description\":\"航空公司（承运人）两字码\",\"children\":[]},{\"name\":\"DepartureDateTime\",\"type\":\"object\",\"quantity\":\"1\",\"default\":\"\",\"description\":\"日期时间,格式：YYYY-MM-DDTHH:MI\",\"children\":[]},{\"name\":\"DepartureCity\",\"type\":\"object\",\"quantity\":\"1\",\"default\":\"\",\"description\":\"\",\"children\":[]},{\"name\":\"ArrivalDateTime\",\"type\":\"object\",\"quantity\":\"0..n\",\"default\":\"\",\"description\":\"日期时间,格式：YYYY-MM-DDTHH:MI\",\"children\":[]},{\"name\":\"ArrivalCity\",\"type\":\"object\",\"quantity\":\"1\",\"default\":\"\",\"description\":\"\",\"children\":[]},{\"name\":\"Equipment\",\"type\":\"array\",\"quantity\":\"0..n\",\"default\":\"\",\"description\":\"机型：1、正常航班：必填；2、OPEN航班：不填写此字段\",\"children\":[]},{\"name\":\"BookingStatus\",\"type\":\"object\",\"quantity\":\"1\",\"default\":\"\",\"description\":\"\",\"children\":[]},{\"name\":\"OperatingCabinCode\",\"type\":\"object\",\"quantity\":\"0..n\",\"default\":\"\",\"description\":\"\",\"children\":[]},{\"name\":\"OperatingFlightNo\",\"type\":\"object\",\"quantity\":\"0..n\",\"default\":\"\",\"description\":\"\",\"children\":[]}]}]},{\"name\":\"NewSegments\",\"type\":\"object\",\"quantity\":\"1\",\"default\":\"\",\"description\":\"变更行程的筛选 条件：变更行程的筛选 条件\",\"children\":[{\"name\":\"NewSegment\",\"type\":\"object\",\"quantity\":\"0..16\",\"default\":\"\",\"description\":\"变更行程的筛选 条件\",\"children\":[{\"name\":\"Origin\",\"type\":\"object\",\"quantity\":\"1\",\"default\":\"\",\"description\":\"变更航段起始地\",\"children\":[{\"name\":\"Name\",\"type\":\"object\",\"quantity\":\"1\",\"default\":\"\",\"description\":\"\",\"children\":[]},{\"name\":\"Type\",\"type\":\"object\",\"quantity\":\"1\",\"default\":\"\",\"description\":\"\",\"children\":[]}]},{\"name\":\"Destination\",\"type\":\"object\",\"quantity\":\"1\",\"default\":\"\",\"description\":\"变更航段到达地\",\"children\":[{\"name\":\"Name\",\"type\":\"object\",\"quantity\":\"1\",\"default\":\"\",\"description\":\"\",\"children\":[]},{\"name\":\"Type\",\"type\":\"object\",\"quantity\":\"1\",\"default\":\"\",\"description\":\"\",\"children\":[]}]},{\"name\":\"FlexInterval\",\"type\":\"array\",\"quantity\":\"0..n\",\"default\":\"\",\"description\":\"\",\"children\":[{\"name\":\"From\",\"type\":\"object\",\"quantity\":\"1\",\"default\":\"\",\"description\":\"\",\"children\":[]},{\"name\":\"To\",\"type\":\"object\",\"quantity\":\"1\",\"default\":\"\",\"description\":\"\",\"children\":[]}]},{\"name\":\"DepartDate\",\"type\":\"object\",\"quantity\":\"1\",\"default\":\"\",\"description\":\"\",\"children\":[]},{\"name\":\"DepartBeforeTime\",\"type\":\"object\",\"quantity\":\"0..n\",\"default\":\"\",\"description\":\"\",\"children\":[]},{\"name\":\"DepartAfterTime\",\"type\":\"object\",\"quantity\":\"0..n\",\"default\":\"\",\"description\":\"\",\"children\":[]},{\"name\":\"CoveredSegments\",\"type\":\"object\",\"quantity\":\"1\",\"default\":\"\",\"description\":\"新行程对应的旧 航段信息：当前仅支持航段一对一的变更，且不能 变更 OD\",\"children\":[{\"name\":\"FlightId\",\"type\":\"object\",\"quantity\":\"0..16\",\"default\":\"\",\"description\":\"\",\"children\":[]}]}]}]},{\"name\":\"ReshopPreference\",\"type\":\"object\",\"quantity\":\"0..n\",\"default\":\"\",\"description\":\"\",\"children\":[{\"name\":\"FareRuleRestriction\",\"type\":\"object\",\"quantity\":\"1\",\"default\":\"\",\"description\":\"国际运价的参数：取值为 true，则新运价必须是可变更\",\"children\":[{\"name\":\"Changeable\",\"type\":\"boolean\",\"quantity\":\"0..n\",\"default\":\"\",\"description\":\"\",\"children\":[]},{\"name\":\"Refundable\",\"type\":\"boolean\",\"quantity\":\"0..n\",\"default\":\"\",\"description\":\"\",\"children\":[]},{\"name\":\"upgradable\",\"type\":\"boolean\",\"quantity\":\"0..n\",\"default\":\"\",\"description\":\"\",\"children\":[]}]},{\"name\":\"FareTypes\",\"type\":\"array\",\"quantity\":\"0..n\",\"default\":\"\",\"description\":\"新票运价类型， 可指定一个或者 多个\",\"children\":[{\"name\":\"FareType\",\"type\":\"array\",\"quantity\":\"0..4\",\"default\":\"\",\"description\":\"PUBLIC：公布运价 PRIVATE：私有/协议运价\\n\\t\\t\\t\\t\\t\\t\\t\\t\\tIT_PUBLIC：IT公布运价\\n\\t\\t\\t\\t\\t\\t\\t\\t\\tIT_PRIVATE：IT私有/协议运价\",\"children\":[]}]},{\"name\":\"AccountCode\",\"type\":\"array\",\"quantity\":\"0..n\",\"default\":\"\",\"description\":\"金额\",\"children\":[{\"name\":\"Code\",\"type\":\"object\",\"quantity\":\"1\",\"default\":\"\",\"description\":\"\",\"children\":[]},{\"name\":\"AllowBlank\",\"type\":\"boolean\",\"quantity\":\"1\",\"default\":\"\",\"description\":\"true：可以是其他运价；false:必须是此accountCode的运价\",\"children\":[]}]},{\"name\":\"PassengerType\",\"type\":\"array\",\"quantity\":\"0..n\",\"default\":\"\",\"description\":\"\",\"children\":[{\"name\":\"Type\",\"type\":\"object\",\"quantity\":\"1\",\"default\":\"\",\"description\":\"\",\"children\":[]},{\"name\":\"ExactPtcMatch\",\"type\":\"boolean\",\"quantity\":\"1\",\"default\":\"\",\"description\":\"是否返回指定旅客类型的运价\\n\\t\\t\\t\\t\\t\\t\\t\\t\\ttrue:仅返回指定旅客类型的运价；\\n\\t\\t\\t\\t\\t\\t\\t\\t\\tfalse:全部返回\",\"children\":[]}]},{\"name\":\"CurrencyOfPayment\",\"type\":\"object\",\"quantity\":\"0..n\",\"default\":\"\",\"description\":\"新票的支付货币代码\",\"children\":[]},{\"name\":\"Waiver\",\"type\":\"array\",\"quantity\":\"0..n\",\"default\":\"\",\"description\":\"豁免代码:\\n\\t\\t\\t\\t\\t\\t01  DEATH\\n\\t\\t\\t\\t\\t\\t02  ILLNESS\\n\\t\\t\\t\\t\\t\\t03  ACT_OF_GOD\\n\\t\\t\\t\\t\\t\\t04 COURT_APPEARANCE\\n\\t\\t\\t\\t\\t\\t05 MILITARY\\n\\t\\t\\t\\t\\t\\t06 TOUR_PACKAGE\\n\\t\\t\\t\\t\\t\\t07 LACK_DOCUMENTATION\",\"children\":[]},{\"name\":\"FlightPreference\",\"type\":\"array\",\"quantity\":\"0..n\",\"default\":\"\",\"description\":\"航班的偏好信息\",\"children\":[{\"name\":\"Cabins\",\"type\":\"array\",\"quantity\":\"0..n\",\"default\":\"\",\"description\":\"舱位等级\",\"children\":[{\"name\":\"Cabin\",\"type\":\"array\",\"quantity\":\"0..99\",\"default\":\"\",\"description\":\"舱位等级：ECONOMY 、PREMIUM_ECONOMY 、BUSINESS、 FIRST、Y 、W 、C、 F等\",\"children\":[]}]},{\"name\":\"AllowCodeshare\",\"type\":\"boolean\",\"quantity\":\"0..n\",\"default\":\"\",\"description\":\"是否允许返回代码共享航班可以不设置，默认为true，表示允许返回代码共享航班\",\"children\":[]},{\"name\":\"AllowInterline\",\"type\":\"boolean\",\"quantity\":\"0..n\",\"default\":\"\",\"description\":\"是否允许返回联运航班，可以不设置，默认为true\\n\\t\\t\\t\\t\\t\\t\\t\\t\\tture-联运结果允许online和interline\\n\\t\\t\\t\\t\\t\\t\\t\\t\\tfalse-联运结果仅返回online\",\"children\":[]},{\"name\":\"FlightsAllowedMarketingCarriers\",\"type\":\"array\",\"quantity\":\"0..n\",\"default\":\"\",\"description\":\"允许的市场方航 司：可以不设置，默认为空，表示允许所有 市场方航空公司，设置后不能使用 flightsForbiddenMarketingCarrier\",\"children\":[{\"name\":\"Carrier\",\"type\":\"object\",\"quantity\":\"0..99\",\"default\":\"\",\"description\":\"航空公司（承运人）两字码\",\"children\":[]}]},{\"name\":\"FlightsForbiddenMarketingCarriers\",\"type\":\"array\",\"quantity\":\"0..n\",\"default\":\"\",\"description\":\"不允许返回的承运方航司,可以不设置，默认为空，表示允许所有承运方航空公司，设置后不能使用flightsAllowedMarketingCarriers\",\"children\":[{\"name\":\"Carrier\",\"type\":\"object\",\"quantity\":\"0..99\",\"default\":\"\",\"description\":\"航空公司（承运人）两字码\",\"children\":[]}]},{\"name\":\"FaresAllowedCarriers\",\"type\":\"array\",\"quantity\":\"0..n\",\"default\":\"\",\"description\":\"可以使用所有航 空公司发布的运 价：可以不设置，默认为空，表示可以使用 所有航空公司发布的运价；设置后表示 只能使用这些航空公司的运\",\"children\":[{\"name\":\"Carrier\",\"type\":\"object\",\"quantity\":\"0..99\",\"default\":\"\",\"description\":\"航空公司（承运人）两字码\",\"children\":[]}]},{\"name\":\"FlightsAllowedOperatingCarriers\",\"type\":\"array\",\"quantity\":\"0..n\",\"default\":\"\",\"description\":\"允许返回的承运航司,可以不设置，默认为空，表示可以使用所有航空公司发布的运价；设置后表示只能使用这些航空公司的运价\",\"children\":[{\"name\":\"Carrier\",\"type\":\"object\",\"quantity\":\"0..99\",\"default\":\"\",\"description\":\"航空公司（承运人）两字码\",\"children\":[]}]},{\"name\":\"ProcessVirtualCabinCombos\",\"type\":\"boolean\",\"quantity\":\"0..1\",\"default\":\"\",\"description\":\"\",\"children\":[]},{\"name\":\"CabinCombo\",\"type\":\"array\",\"quantity\":\"0..1\",\"default\":\"\",\"description\":\"\",\"children\":[]},{\"name\":\"BrandSource\",\"type\":\"array\",\"quantity\":\"0..1\",\"default\":\"\",\"description\":\"\",\"children\":[]},{\"name\":\"BrandCommercialName\",\"type\":\"string\",\"quantity\":\"0..1\",\"default\":\"\",\"description\":\"\",\"children\":[]}]}]}]}]",
    "responseSchema": "[{\"name\":\"TRR_VoluntaryReshopRS\",\"type\":\"object\",\"quantity\":\"1\",\"default\":\"\",\"description\":\"\",\"children\":[{\"name\":\"ProcessResult\",\"type\":\"array\",\"quantity\":\"1..1\",\"default\":\"\",\"description\":\"reshop 结果的状态\",\"children\":[{\"name\":\"Status\",\"type\":\"object\",\"quantity\":\"1\",\"default\":\"\",\"description\":\"状态：取值： OK：座位 confirmed RQ：waitlist SA：standby NS：不占座婴儿OPEN：OPEN 航段ARNK：地面段\",\"children\":[]},{\"name\":\"Messages\",\"type\":\"array\",\"quantity\":\"0..1\",\"default\":\"\",\"description\":\"\",\"children\":[{\"name\":\"Message\",\"type\":\"object\",\"quantity\":\"0..10\",\"default\":\"\",\"description\":\"\",\"children\":[{\"name\":\"MessageType\",\"type\":\"object\",\"quantity\":\"1\",\"default\":\"\",\"description\":\"\",\"children\":[]},{\"name\":\"Code\",\"type\":\"string\",\"quantity\":\"1\",\"default\":\"\",\"description\":\"税代码：税代码\",\"children\":[]},{\"name\":\"Text\",\"type\":\"string\",\"quantity\":\"1\",\"default\":\"\",\"description\":\"\",\"children\":[]}]}]}]},{\"name\":\"DataLibrary\",\"type\":\"object\",\"quantity\":\"0..1\",\"default\":\"\",\"description\":\"\",\"children\":[{\"name\":\"Passengers\",\"type\":\"array\",\"quantity\":\"1..1\",\"default\":\"\",\"description\":\"\",\"children\":[{\"name\":\"Passenger\",\"type\":\"object\",\"quantity\":\"1..n\",\"default\":\"\",\"description\":\"\",\"children\":[{\"name\":\"Id\",\"type\":\"string\",\"quantity\":\"1\",\"default\":\"\",\"description\":\"\",\"children\":[]},{\"name\":\"Ptcs\",\"type\":\"object\",\"quantity\":\"1\",\"default\":\"\",\"description\":\"\",\"children\":[{\"name\":\"PassengerType\",\"type\":\"object\",\"quantity\":\"1\",\"default\":\"\",\"description\":\"旅客类型：旅客类型，如 1 名旅客有多个 PTC，可 以都写上。\",\"children\":[]}]},{\"name\":\"CurrencyOfPayment\",\"type\":\"object\",\"quantity\":\"0..1\",\"default\":\"\",\"description\":\"\",\"children\":[]},{\"name\":\"Waiver\",\"type\":\"array\",\"quantity\":\"0..1\",\"default\":\"\",\"description\":\"如果豁免适用，此处输出以下取值：\\n\\t\\t\\t\\t\\t\\tACT_OF_GOD\\n\\t\\t\\t\\t\\t\\tCOURT_APPEARANCE\\n\\t\\t\\t\\t\\t\\tDEATH\\n\\t\\t\\t\\t\\t\\tILLNESS\\n\\t\\t\\t\\t\\t\\tLACK_DOCUMENTATION\\n\\t\\t\\t\\t\\t\\tMILITARY\\n\\t\\t\\t\\t\\t\\tTOUR_PACKAGE\\n\\t\\t\\t\\t\\t\\t与TRI指令对应关系如下：\\n\\t\\t\\t\\t\\t\\t01 DEATH\\n\\t\\t\\t\\t\\t\\t02 ILLNESS\\n\\t\\t\\t\\t\\t\\t03 ACT_OF_GOD\\n\\t\\t\\t\\t\\t\\t04 COURT_APPEARANCE\\n\\t\\t\\t\\t\\t\\t05 MILITARY\\n\\t\\t\\t\\t\\t\\t06 TOUR_PACKAGE\\n\\t\\t\\t\\t\\t\\t07 LACK_DOCUMENTATION\",\"children\":[]}]}]},{\"name\":\"Fares\",\"type\":\"array\",\"quantity\":\"1..1\",\"default\":\"\",\"description\":\"\",\"children\":[{\"name\":\"Fare\",\"type\":\"object\",\"quantity\":\"1..n\",\"default\":\"\",\"description\":\"\",\"children\":[{\"name\":\"Id\",\"type\":\"string\",\"quantity\":\"1..1\",\"default\":\"\",\"description\":\"\",\"children\":[]},{\"name\":\"Origin\",\"type\":\"object\",\"quantity\":\"1..1\",\"default\":\"\",\"description\":\"运价始发地：票价的始发地。输出为：机场或城市 三字码。\",\"children\":[]},{\"name\":\"Destination\",\"type\":\"object\",\"quantity\":\"1..1\",\"default\":\"\",\"description\":\"运价目的地：票价的目的地。输出为：机场或城市 三字码。\",\"children\":[]},{\"name\":\"Carrier\",\"type\":\"object\",\"quantity\":\"1..1\",\"default\":\"\",\"description\":\"航空公司（承运人）两字码\",\"children\":[]},{\"name\":\"Fbc\",\"type\":\"string\",\"quantity\":\"0..1\",\"default\":\"\",\"description\":\"运价基础：票价的运价基础。不含 Ticketing code modifier 和 Ticketing designators 的运价基础。 可以不填\",\"children\":[]},{\"name\":\"RuleTariff\",\"type\":\"string\",\"quantity\":\"0..1\",\"default\":\"\",\"description\":\"运价的 rule tariff：输出运价的 tariff。这是按航线选择的值，航司在运价发布的时候就做好了 coding，直接输出。\",\"children\":[]},{\"name\":\"Rule\",\"type\":\"string\",\"quantity\":\"0..1\",\"default\":\"\",\"description\":\"运价的 rule number：输出运价的 rule。这是航空公司自己编的 4 位字符，可以是数字也可以是字母。\",\"children\":[]},{\"name\":\"Private\",\"type\":\"boolean\",\"quantity\":\"1..1\",\"default\":\"\",\"description\":\"是否私有：用于表示运价是否是私有true：是私有运价false：不是私有运价\",\"children\":[]},{\"name\":\"FareDataForReprice\",\"type\":\"string\",\"quantity\":\"0..1\",\"default\":\"\",\"description\":\"Fare信息\",\"children\":[]},{\"name\":\"FareDataForDiagnostics\",\"type\":\"boolean\",\"quantity\":\"0..1\",\"default\":\"\",\"description\":\"Fare信息\",\"children\":[]},{\"name\":\"PrimeRbds\",\"type\":\"object\",\"quantity\":\"1\",\"default\":\"\",\"description\":\"主RBD\",\"children\":[{\"name\":\"Rbd\",\"type\":\"string\",\"quantity\":\"1..n\",\"default\":\"\",\"description\":\"订座舱位：订座舱位\",\"children\":[]}]},{\"name\":\"FbcOverride\",\"type\":\"string\",\"quantity\":\"1..1\",\"default\":\"\",\"description\":\"打在票上的运价基础：是包含 Ticketing code modifier 的 运价基础。\",\"children\":[]},{\"name\":\"TicketDesignator1\",\"type\":\"string\",\"quantity\":\"1..1\",\"default\":\"\",\"description\":\"ticketDesignator1：ticketDesignator1，通常为 CH75 或NW 等尾缀。但是从票上无法得知尾缀到底是 TD1 还是 TD2，所以把所有尾缀都放在 TD1 中。8 位，不满加空格\",\"children\":[]},{\"name\":\"Tier\",\"type\":\"string\",\"quantity\":\"0..1\",\"default\":\"\",\"description\":\"tier\",\"children\":[]},{\"name\":\"BrandName\",\"type\":\"string\",\"quantity\":\"0..1\",\"default\":\"\",\"description\":\"品牌名\",\"children\":[]},{\"name\":\"Penalty\",\"type\":\"object\",\"quantity\":\"1\",\"default\":\"\",\"description\":\"\",\"children\":[{\"name\":\"Change\",\"type\":\"array\",\"quantity\":\"1..1\",\"default\":\"\",\"description\":\"换开\",\"children\":[{\"name\":\"BeforeDeparture\",\"type\":\"object\",\"quantity\":\"1..1\",\"default\":\"\",\"description\":\"全部未使用\",\"children\":[{\"name\":\"Allowed\",\"type\":\"boolean\",\"quantity\":\"1..1\",\"default\":\"\",\"description\":\"是否允许全部未使用换开：是否允许全部未使用换开。取值true：允许\",\"children\":[]},{\"name\":\"Price\",\"type\":\"object\",\"quantity\":\"1..1\",\"default\":\"\",\"description\":\"税金：税金\",\"children\":[{\"name\":\"Amount\",\"type\":\"string\",\"quantity\":\"1..1\",\"default\":\"\",\"description\":\"金额：金额\",\"children\":[]},{\"name\":\"Currency\",\"type\":\"object\",\"quantity\":\"1..1\",\"default\":\"\",\"description\":\"货币：货币（同新票支付货币）\",\"children\":[]}]}]},{\"name\":\"AfterDeparture\",\"type\":\"object\",\"quantity\":\"1..1\",\"default\":\"\",\"description\":\"\",\"children\":[{\"name\":\"Allowed\",\"type\":\"boolean\",\"quantity\":\"1..1\",\"default\":\"\",\"description\":\"是否允许全部未使用换开：是否允许全部未使用换开。取值true：允许\",\"children\":[]},{\"name\":\"Price\",\"type\":\"object\",\"quantity\":\"1..1\",\"default\":\"\",\"description\":\"税金：税金\",\"children\":[{\"name\":\"Amount\",\"type\":\"string\",\"quantity\":\"1..1\",\"default\":\"\",\"description\":\"金额：金额\",\"children\":[]},{\"name\":\"Currency\",\"type\":\"object\",\"quantity\":\"1..1\",\"default\":\"\",\"description\":\"货币：货币（同新票支付货币）\",\"children\":[]}]}]}]},{\"name\":\"Refund\",\"type\":\"array\",\"quantity\":\"1..1\",\"default\":\"\",\"description\":\"退票\",\"children\":[{\"name\":\"BeforeDeparture\",\"type\":\"object\",\"quantity\":\"1..1\",\"default\":\"\",\"description\":\"\",\"children\":[{\"name\":\"Allowed\",\"type\":\"boolean\",\"quantity\":\"1..1\",\"default\":\"\",\"description\":\"是否允许全部未使用换开：是否允许全部未使用换开。取值true：允许\",\"children\":[]},{\"name\":\"Price\",\"type\":\"object\",\"quantity\":\"1..1\",\"default\":\"\",\"description\":\"税金：税金\",\"children\":[{\"name\":\"Amount\",\"type\":\"string\",\"quantity\":\"1..1\",\"default\":\"\",\"description\":\"金额：金额\",\"children\":[]},{\"name\":\"Currency\",\"type\":\"object\",\"quantity\":\"1..1\",\"default\":\"\",\"description\":\"货币：货币（同新票支付货币）\",\"children\":[]}]}]},{\"name\":\"AfterDeparture\",\"type\":\"object\",\"quantity\":\"1..1\",\"default\":\"\",\"description\":\"\",\"children\":[{\"name\":\"Allowed\",\"type\":\"boolean\",\"quantity\":\"1..1\",\"default\":\"\",\"description\":\"是否允许全部未使用换开：是否允许全部未使用换开。取值true：允许\",\"children\":[]},{\"name\":\"Price\",\"type\":\"object\",\"quantity\":\"1..1\",\"default\":\"\",\"description\":\"税金：税金\",\"children\":[{\"name\":\"Amount\",\"type\":\"string\",\"quantity\":\"1..1\",\"default\":\"\",\"description\":\"金额：金额\",\"children\":[]},{\"name\":\"Currency\",\"type\":\"object\",\"quantity\":\"1..1\",\"default\":\"\",\"description\":\"货币：货币（同新票支付货币）\",\"children\":[]}]}]}]},{\"name\":\"Noshow\",\"type\":\"array\",\"quantity\":\"1..1\",\"default\":\"\",\"description\":\"noshow\",\"children\":[{\"name\":\"Allowed\",\"type\":\"boolean\",\"quantity\":\"1..1\",\"default\":\"\",\"description\":\"\",\"children\":[]},{\"name\":\"Price\",\"type\":\"object\",\"quantity\":\"1..1\",\"default\":\"\",\"description\":\"\",\"children\":[{\"name\":\"Amount\",\"type\":\"string\",\"quantity\":\"1..1\",\"default\":\"\",\"description\":\"金额：金额\",\"children\":[]},{\"name\":\"Currency\",\"type\":\"object\",\"quantity\":\"1..1\",\"default\":\"\",\"description\":\"货币：货币（同新票支付货币）\",\"children\":[]}]}]}]},{\"name\":\"BrandDefinition\",\"type\":\"object\",\"quantity\":\"1\",\"default\":\"\",\"description\":\"品牌定义\",\"children\":[{\"name\":\"OfferedForFree\",\"type\":\"object\",\"quantity\":\"0..n\",\"default\":\"\",\"description\":\"免费服务\",\"children\":[{\"name\":\"Code\",\"type\":\"string\",\"quantity\":\"0..1\",\"default\":\"\",\"description\":\"\",\"children\":[]},{\"name\":\"SubCode\",\"type\":\"string\",\"quantity\":\"0..1\",\"default\":\"\",\"description\":\"\",\"children\":[]},{\"name\":\"Group\",\"type\":\"string\",\"quantity\":\"0..1\",\"default\":\"\",\"description\":\"\",\"children\":[]},{\"name\":\"SubGroup\",\"type\":\"string\",\"quantity\":\"0..1\",\"default\":\"\",\"description\":\"\",\"children\":[]},{\"name\":\"Description1\",\"type\":\"string\",\"quantity\":\"0..1\",\"default\":\"\",\"description\":\"\",\"children\":[]},{\"name\":\"Description2\",\"type\":\"string\",\"quantity\":\"0..1\",\"default\":\"\",\"description\":\"\",\"children\":[]},{\"name\":\"SsrCode\",\"type\":\"string\",\"quantity\":\"0..1\",\"default\":\"\",\"description\":\"\",\"children\":[]},{\"name\":\"CommercialName\",\"type\":\"string\",\"quantity\":\"0..1\",\"default\":\"\",\"description\":\"\",\"children\":[]},{\"name\":\"AdditionalInformation\",\"type\":\"string\",\"quantity\":\"0..1\",\"default\":\"\",\"description\":\"\",\"children\":[]},{\"name\":\"MediaId\",\"type\":\"string\",\"quantity\":\"0..1\",\"default\":\"\",\"description\":\"\",\"children\":[]}]},{\"name\":\"OfferedForCharge\",\"type\":\"object\",\"quantity\":\"0..n\",\"default\":\"\",\"description\":\"付费服务\",\"children\":[{\"name\":\"Code\",\"type\":\"string\",\"quantity\":\"0..1\",\"default\":\"\",\"description\":\"\",\"children\":[]},{\"name\":\"SubCode\",\"type\":\"string\",\"quantity\":\"0..1\",\"default\":\"\",\"description\":\"\",\"children\":[]},{\"name\":\"Group\",\"type\":\"string\",\"quantity\":\"0..1\",\"default\":\"\",\"description\":\"\",\"children\":[]},{\"name\":\"SubGroup\",\"type\":\"string\",\"quantity\":\"0..1\",\"default\":\"\",\"description\":\"\",\"children\":[]},{\"name\":\"Description1\",\"type\":\"string\",\"quantity\":\"0..1\",\"default\":\"\",\"description\":\"\",\"children\":[]},{\"name\":\"Description2\",\"type\":\"string\",\"quantity\":\"0..1\",\"default\":\"\",\"description\":\"\",\"children\":[]},{\"name\":\"SsrCode\",\"type\":\"string\",\"quantity\":\"0..1\",\"default\":\"\",\"description\":\"\",\"children\":[]},{\"name\":\"CommercialName\",\"type\":\"string\",\"quantity\":\"0..1\",\"default\":\"\",\"description\":\"\",\"children\":[]},{\"name\":\"AdditionalInformation\",\"type\":\"string\",\"quantity\":\"0..1\",\"default\":\"\",\"description\":\"\",\"children\":[]},{\"name\":\"MediaId\",\"type\":\"string\",\"quantity\":\"0..1\",\"default\":\"\",\"description\":\"\",\"children\":[]}]},{\"name\":\"DisplayAsNotOffered\",\"type\":\"object\",\"quantity\":\"0..n\",\"default\":\"\",\"description\":\"仅显示但不提供的服务\",\"children\":[{\"name\":\"Code\",\"type\":\"string\",\"quantity\":\"0..1\",\"default\":\"\",\"description\":\"\",\"children\":[]},{\"name\":\"SubCode\",\"type\":\"string\",\"quantity\":\"0..1\",\"default\":\"\",\"description\":\"\",\"children\":[]},{\"name\":\"Group\",\"type\":\"string\",\"quantity\":\"0..1\",\"default\":\"\",\"description\":\"\",\"children\":[]},{\"name\":\"SubGroup\",\"type\":\"string\",\"quantity\":\"0..1\",\"default\":\"\",\"description\":\"\",\"children\":[]},{\"name\":\"Description1\",\"type\":\"string\",\"quantity\":\"0..1\",\"default\":\"\",\"description\":\"\",\"children\":[]},{\"name\":\"Description2\",\"type\":\"string\",\"quantity\":\"0..1\",\"default\":\"\",\"description\":\"\",\"children\":[]},{\"name\":\"SsrCode\",\"type\":\"string\",\"quantity\":\"0..1\",\"default\":\"\",\"description\":\"\",\"children\":[]},{\"name\":\"CommercialName\",\"type\":\"string\",\"quantity\":\"0..1\",\"default\":\"\",\"description\":\"\",\"children\":[]},{\"name\":\"AdditionalInformation\",\"type\":\"string\",\"quantity\":\"0..1\",\"default\":\"\",\"description\":\"\",\"children\":[]},{\"name\":\"MediaId\",\"type\":\"string\",\"quantity\":\"0..1\",\"default\":\"\",\"description\":\"\",\"children\":[]}]},{\"name\":\"NotOffered\",\"type\":\"object\",\"quantity\":\"0..n\",\"default\":\"\",\"description\":\"不提供的服务\",\"children\":[{\"name\":\"Code\",\"type\":\"string\",\"quantity\":\"0..1\",\"default\":\"\",\"description\":\"\",\"children\":[]},{\"name\":\"SubCode\",\"type\":\"string\",\"quantity\":\"0..1\",\"default\":\"\",\"description\":\"\",\"children\":[]},{\"name\":\"Group\",\"type\":\"string\",\"quantity\":\"0..1\",\"default\":\"\",\"description\":\"\",\"children\":[]},{\"name\":\"SubGroup\",\"type\":\"string\",\"quantity\":\"0..1\",\"default\":\"\",\"description\":\"\",\"children\":[]},{\"name\":\"Description1\",\"type\":\"string\",\"quantity\":\"0..1\",\"default\":\"\",\"description\":\"\",\"children\":[]},{\"name\":\"Description2\",\"type\":\"string\",\"quantity\":\"0..1\",\"default\":\"\",\"description\":\"\",\"children\":[]},{\"name\":\"SsrCode\",\"type\":\"string\",\"quantity\":\"0..1\",\"default\":\"\",\"description\":\"\",\"children\":[]},{\"name\":\"CommercialName\",\"type\":\"string\",\"quantity\":\"0..1\",\"default\":\"\",\"description\":\"\",\"children\":[]},{\"name\":\"AdditionalInformation\",\"type\":\"string\",\"quantity\":\"0..1\",\"default\":\"\",\"description\":\"\",\"children\":[]},{\"name\":\"MediaId\",\"type\":\"string\",\"quantity\":\"0..1\",\"default\":\"\",\"description\":\"\",\"children\":[]}]}]}]}]},{\"name\":\"Flights\",\"type\":\"array\",\"quantity\":\"1..1\",\"default\":\"\",\"description\":\"\",\"children\":[{\"name\":\"Flight\",\"type\":\"object\",\"quantity\":\"1..n\",\"default\":\"\",\"description\":\"\",\"children\":[{\"name\":\"Id\",\"type\":\"string\",\"quantity\":\"1\",\"default\":\"\",\"description\":\"\",\"children\":[]},{\"name\":\"RepriceStatus\",\"type\":\"object\",\"quantity\":\"1\",\"default\":\"\",\"description\":\"换开状态：换开状态。3 种取值：FLOWN/ KEEP/ 空FLOWN： 已飞航段 KEEP：未变更航段 空：除 FLOWN 和 KEEP 以外的航段\",\"children\":[]},{\"name\":\"MarketingCarrier\",\"type\":\"object\",\"quantity\":\"1\",\"default\":\"\",\"description\":\"航空公司（承运人）两字码\",\"children\":[]},{\"name\":\"MarketingFlightNumber\",\"type\":\"string\",\"quantity\":\"1\",\"default\":\"\",\"description\":\"市场方航空公司航班号：就是航班号。 取值：航班号、OPEN。航班号：数字； 航班OPEN：如果当前航段是OPEN航段，那么此处输出 OPEN，相应的 bookingstatus 也输出 OPEN\",\"children\":[]},{\"name\":\"OperatingCarrier\",\"type\":\"object\",\"quantity\":\"1\",\"default\":\"\",\"description\":\"承运方航空公司：航空公司两字码 注：最后有一空格\",\"children\":[]},{\"name\":\"DepartureAirport\",\"type\":\"object\",\"quantity\":\"1\",\"default\":\"\",\"description\":\"起飞机场：取值：机场三字码\",\"children\":[]},{\"name\":\"DepartureTerminal\",\"type\":\"string\",\"quantity\":\"1\",\"default\":\"\",\"description\":\"起飞航站楼：航站楼代码\",\"children\":[]},{\"name\":\"ArrivalAirport\",\"type\":\"object\",\"quantity\":\"1\",\"default\":\"\",\"description\":\"到达机场：取值：机场三字码\",\"children\":[]},{\"name\":\"ArrivalTerminal\",\"type\":\"string\",\"quantity\":\"1\",\"default\":\"\",\"description\":\"到达航站楼：航站楼代码\",\"children\":[]},{\"name\":\"MealService\",\"type\":\"string\",\"quantity\":\"1\",\"default\":\"\",\"description\":\"餐食信息：餐食\",\"children\":[]},{\"name\":\"ASR\",\"type\":\"boolean\",\"quantity\":\"1\",\"default\":\"\",\"description\":\"ASR 标识：true/false\",\"children\":[]},{\"name\":\"IntermediateAirports\",\"type\":\"object\",\"quantity\":\"1\",\"default\":\"\",\"description\":\"\",\"children\":[{\"name\":\"Airport\",\"type\":\"object\",\"quantity\":\"1\",\"default\":\"\",\"description\":\"\",\"children\":[]},{\"name\":\"GroundTime\",\"type\":\"string\",\"quantity\":\"1\",\"default\":\"\",\"description\":\"经停时间：单位是“分钟”\",\"children\":[]}]},{\"name\":\"StopQuantity\",\"type\":\"string\",\"quantity\":\"1\",\"default\":\"\",\"description\":\"经停点数量：取值为数字\",\"children\":[]},{\"name\":\"DepartureDateTime\",\"type\":\"object\",\"quantity\":\"1\",\"default\":\"\",\"description\":\"起飞时间：YYYY-MM-DDTHH:MI\",\"children\":[]},{\"name\":\"ArrivalDateTime\",\"type\":\"object\",\"quantity\":\"1\",\"default\":\"\",\"description\":\"到达时间：YYYY-MM-DDTHH:MI\",\"children\":[]},{\"name\":\"AircraftTypes\",\"type\":\"object\",\"quantity\":\"1\",\"default\":\"\",\"description\":\"机型\",\"children\":[{\"name\":\"AircraftTypeCode\",\"type\":\"string\",\"quantity\":\"1..10\",\"default\":\"\",\"description\":\"\",\"children\":[]}]},{\"name\":\"Rbd\",\"type\":\"string\",\"quantity\":\"1\",\"default\":\"\",\"description\":\"\",\"children\":[]},{\"name\":\"AvailableSeats\",\"type\":\"string\",\"quantity\":\"1\",\"default\":\"\",\"description\":\"\",\"children\":[]},{\"name\":\"AvailabilityInfo\",\"type\":\"array\",\"quantity\":\"0..n\",\"default\":\"\",\"description\":\"\",\"children\":[{\"name\":\"Rbd\",\"type\":\"string\",\"quantity\":\"1\",\"default\":\"\",\"description\":\"\",\"children\":[]},{\"name\":\"Seats\",\"type\":\"string\",\"quantity\":\"1\",\"default\":\"\",\"description\":\"\",\"children\":[]}]}]}]},{\"name\":\"Taxes\",\"type\":\"array\",\"quantity\":\"0..n\",\"default\":\"\",\"description\":\"\",\"children\":[{\"name\":\"Tax\",\"type\":\"object\",\"quantity\":\"1\",\"default\":\"\",\"description\":\"税代码\",\"children\":[{\"name\":\"Id\",\"type\":\"string\",\"quantity\":\"1\",\"default\":\"\",\"description\":\"\",\"children\":[]},{\"name\":\"Category\",\"type\":\"object\",\"quantity\":\"1\",\"default\":\"\",\"description\":\"税的种类：取值：YQ_YR/ IATA YQ_YR：当该税属于燃油税时IATA：当该税不属于燃油税时\",\"children\":[]},{\"name\":\"Carrier\",\"type\":\"object\",\"quantity\":\"1\",\"default\":\"\",\"description\":\"航空公司（承运人）两字码\",\"children\":[]},{\"name\":\"Price\",\"type\":\"object\",\"quantity\":\"1\",\"default\":\"\",\"description\":\"\",\"children\":[{\"name\":\"Amount\",\"type\":\"string\",\"quantity\":\"1..1\",\"default\":\"\",\"description\":\"金额：金额\",\"children\":[]},{\"name\":\"Currency\",\"type\":\"object\",\"quantity\":\"1..1\",\"default\":\"\",\"description\":\"货币：货币（同新票支付货币）\",\"children\":[]}]},{\"name\":\"Code\",\"type\":\"string\",\"quantity\":\"1\",\"default\":\"\",\"description\":\"\",\"children\":[]},{\"name\":\"Airports\",\"type\":\"object\",\"quantity\":\"1\",\"default\":\"\",\"description\":\"\",\"children\":[{\"name\":\"Airport\",\"type\":\"object\",\"quantity\":\"1..16\",\"default\":\"\",\"description\":\"\",\"children\":[]}]}]}]},{\"name\":\"TicketMasks\",\"type\":\"object\",\"quantity\":\"1\",\"default\":\"\",\"description\":\"\",\"children\":[{\"name\":\"TicketMask\",\"type\":\"object\",\"quantity\":\"1\",\"default\":\"\",\"description\":\"\",\"children\":[{\"name\":\"Id\",\"type\":\"string\",\"quantity\":\"1\",\"default\":\"\",\"description\":\"\",\"children\":[]},{\"name\":\"IssueInformation\",\"type\":\"object\",\"quantity\":\"1\",\"default\":\"\",\"description\":\"\",\"children\":[{\"name\":\"SellerId\",\"type\":\"string\",\"quantity\":\"1\",\"default\":\"\",\"description\":\"seller：该 offer 的 seller。从 response 的 dataLibrary-sellers 中来的。\",\"children\":[]},{\"name\":\"Country\",\"type\":\"string\",\"quantity\":\"1\",\"default\":\"\",\"description\":\"出票国家：默认为 POS 所在国家\",\"children\":[]},{\"name\":\"DateTime\",\"type\":\"object\",\"quantity\":\"1\",\"default\":\"\",\"description\":\"出票时间：YYYY-MM-DDTHH:MI\",\"children\":[]},{\"name\":\"AccountCode\",\"type\":\"string\",\"quantity\":\"1\",\"default\":\"\",\"description\":\"大客户编码：当原票需要指定 account code（以下 简称 AC）计算时。这里指定 AC 是指仅\",\"children\":[]}]},{\"name\":\"PlatingCarrier\",\"type\":\"object\",\"quantity\":\"1\",\"default\":\"\",\"description\":\"出票航空公司：航空公司两字码 注：最后有一空格\",\"children\":[]},{\"name\":\"OrigDest\",\"type\":\"string\",\"quantity\":\"1\",\"default\":\"\",\"description\":\"原票整个行程起飞和到达机场\",\"children\":[]},{\"name\":\"Coupons\",\"type\":\"object\",\"quantity\":\"1\",\"default\":\"\",\"description\":\"\",\"children\":[{\"name\":\"Id\",\"type\":\"object\",\"quantity\":\"1\",\"default\":\"\",\"description\":\"税的 ID 号：dataLibrary-Taxes 中的 id\",\"children\":[]},{\"name\":\"FlightId\",\"type\":\"object\",\"quantity\":\"0..n\",\"default\":\"\",\"description\":\"航班 id：datalibrary-flights 中的 ID\",\"children\":[]},{\"name\":\"FareId\",\"type\":\"string\",\"quantity\":\"1\",\"default\":\"\",\"description\":\"Fare ID：运价的 ID 对应回报里 datalibrary-fares\",\"children\":[]},{\"name\":\"DepAirport\",\"type\":\"string\",\"quantity\":\"1\",\"default\":\"\",\"description\":\"起飞机场：机场三字码\",\"children\":[]},{\"name\":\"ArrAirport\",\"type\":\"string\",\"quantity\":\"1\",\"default\":\"\",\"description\":\"到达机场：机场三字码\",\"children\":[]},{\"name\":\"Status\",\"type\":\"object\",\"quantity\":\"1\",\"default\":\"\",\"description\":\"取值：\\n\\t\\t\\t\\t\\t\\t\\t\\t\\tOK：座位confirmed\\n\\t\\t\\t\\t\\t\\t\\t\\t\\tRQ：waitlist\\n\\t\\t\\t\\t\\t\\t\\t\\t\\tSA：standby\\n\\t\\t\\t\\t\\t\\t\\t\\t\\tNS：不占座婴儿\\n\\t\\t\\t\\t\\t\\t\\t\\t\\tOPEN：OPEN航段\\n\\t\\t\\t\\t\\t\\t\\t\\t\\tARNK：地面段\",\"children\":[]},{\"name\":\"Stopover\",\"type\":\"object\",\"quantity\":\"1\",\"default\":\"\",\"description\":\"经停点：取值： X：connection point O：stopover point\",\"children\":[]},{\"name\":\"Carrier\",\"type\":\"string\",\"quantity\":\"1\",\"default\":\"\",\"description\":\"市场方航司：航空公司两字码 注：最后有一空格\",\"children\":[]},{\"name\":\"FlightNo\",\"type\":\"string\",\"quantity\":\"1\",\"default\":\"\",\"description\":\"航班号：航班号 如果是 OPEN 航段，此处值为 OPEN\",\"children\":[]},{\"name\":\"Rbd\",\"type\":\"string\",\"quantity\":\"1\",\"default\":\"\",\"description\":\"\",\"children\":[]},{\"name\":\"DepDate\",\"type\":\"string\",\"quantity\":\"1\",\"default\":\"\",\"description\":\"\",\"children\":[]},{\"name\":\"DepTime\",\"type\":\"string\",\"quantity\":\"1\",\"default\":\"\",\"description\":\"\",\"children\":[]},{\"name\":\"FbcPassengerCoupon\",\"type\":\"string\",\"quantity\":\"1\",\"default\":\"\",\"description\":\"Passenger coupon 的运 价基础：Passenger coupon 的运价基础（不包 含 TD）\",\"children\":[]},{\"name\":\"FbcAuditCoupon\",\"type\":\"string\",\"quantity\":\"1\",\"default\":\"\",\"description\":\"Audit coupon 的运价基 础：Audit coupon 的运价基础（不包含 TD）\",\"children\":[]},{\"name\":\"TourCode\",\"type\":\"string\",\"quantity\":\"1\",\"default\":\"\",\"description\":\"Tour code 旅行代码：当有 TC 的时候填写\",\"children\":[]},{\"name\":\"Nvb\",\"type\":\"object\",\"quantity\":\"1\",\"default\":\"\",\"description\":\"NVB 旅行有效期：YYYY-MM-DD\",\"children\":[]},{\"name\":\"Nva\",\"type\":\"object\",\"quantity\":\"1\",\"default\":\"\",\"description\":\"NVA 旅行有效期：YYYY-MM-DD\",\"children\":[]},{\"name\":\"AllowedBaggage\",\"type\":\"array\",\"quantity\":\"1..1\",\"default\":\"\",\"description\":\"\",\"children\":[{\"name\":\"Quantity\",\"type\":\"string\",\"quantity\":\"1..1\",\"default\":\"\",\"description\":\"数量：取值：正整数\",\"children\":[]},{\"name\":\"Unit\",\"type\":\"array\",\"quantity\":\"1..1\",\"default\":\"\",\"description\":\"单位：取值：K：公斤P：磅PC：件 XX：不允许带行李\",\"children\":[]}]}]},{\"name\":\"FareInformation\",\"type\":\"object\",\"quantity\":\"1\",\"default\":\"\",\"description\":\"\",\"children\":[{\"name\":\"BaseFare\",\"type\":\"object\",\"quantity\":\"1\",\"default\":\"\",\"description\":\"新票票面价\",\"children\":[{\"name\":\"Amount\",\"type\":\"string\",\"quantity\":\"1..1\",\"default\":\"\",\"description\":\"金额：金额\",\"children\":[]},{\"name\":\"Currency\",\"type\":\"object\",\"quantity\":\"1..1\",\"default\":\"\",\"description\":\"货币：货币（同新票支付货币）\",\"children\":[]}]},{\"name\":\"EquivalentFare\",\"type\":\"object\",\"quantity\":\"1\",\"default\":\"\",\"description\":\"\",\"children\":[{\"name\":\"Amount\",\"type\":\"string\",\"quantity\":\"1..1\",\"default\":\"\",\"description\":\"金额：金额\",\"children\":[]},{\"name\":\"Currency\",\"type\":\"object\",\"quantity\":\"1..1\",\"default\":\"\",\"description\":\"货币：货币（同新票支付货币）\",\"children\":[]}]},{\"name\":\"ETicketTaxes\",\"type\":\"object\",\"quantity\":\"1\",\"default\":\"\",\"description\":\"\",\"children\":[{\"name\":\"Tax1\",\"type\":\"string\",\"quantity\":\"1\",\"default\":\"\",\"description\":\"\",\"children\":[]},{\"name\":\"Tax2\",\"type\":\"string\",\"quantity\":\"1\",\"default\":\"\",\"description\":\"\",\"children\":[]},{\"name\":\"Tax3\",\"type\":\"string\",\"quantity\":\"1\",\"default\":\"\",\"description\":\"\",\"children\":[]}]},{\"name\":\"IataTaxes\",\"type\":\"object\",\"quantity\":\"0..1\",\"default\":\"\",\"description\":\"\",\"children\":[{\"name\":\"Id\",\"type\":\"string\",\"quantity\":\"1..16\",\"default\":\"\",\"description\":\"\",\"children\":[]}]},{\"name\":\"Yqyr\",\"type\":\"object\",\"quantity\":\"0..1\",\"default\":\"\",\"description\":\"\",\"children\":[{\"name\":\"Id\",\"type\":\"string\",\"quantity\":\"1..16\",\"default\":\"\",\"description\":\"\",\"children\":[]}]},{\"name\":\"XfTaxes\",\"type\":\"object\",\"quantity\":\"0..1\",\"default\":\"\",\"description\":\"\",\"children\":[{\"name\":\"Id\",\"type\":\"string\",\"quantity\":\"1..16\",\"default\":\"\",\"description\":\"\",\"children\":[]}]},{\"name\":\"ZpTaxes\",\"type\":\"object\",\"quantity\":\"0..1\",\"default\":\"\",\"description\":\"\",\"children\":[{\"name\":\"Id\",\"type\":\"string\",\"quantity\":\"1..16\",\"default\":\"\",\"description\":\"\",\"children\":[]}]},{\"name\":\"TotalFare\",\"type\":\"object\",\"quantity\":\"1\",\"default\":\"\",\"description\":\"旅客实付总额（同新票 支付货币）：旅客实付总额（同新票支付货币）\",\"children\":[{\"name\":\"Amount\",\"type\":\"string\",\"quantity\":\"1..1\",\"default\":\"\",\"description\":\"金额：金额\",\"children\":[]},{\"name\":\"Currency\",\"type\":\"object\",\"quantity\":\"1..1\",\"default\":\"\",\"description\":\"货币：货币（同新票支付货币）\",\"children\":[]}]}]},{\"name\":\"ExchangeRates\",\"type\":\"object\",\"quantity\":\"1\",\"default\":\"\",\"description\":\"\",\"children\":[{\"name\":\"Bsr\",\"type\":\"object\",\"quantity\":\"1\",\"default\":\"\",\"description\":\"\",\"children\":[{\"name\":\"FromCurrency\",\"type\":\"object\",\"quantity\":\"1\",\"default\":\"\",\"description\":\"从货币：Base fare 货币\",\"children\":[]},{\"name\":\"ToCurrency\",\"type\":\"object\",\"quantity\":\"1\",\"default\":\"\",\"description\":\"到货币：Equivalent 货币\",\"children\":[]},{\"name\":\"Rate\",\"type\":\"string\",\"quantity\":\"1\",\"default\":\"\",\"description\":\"转换率：转换率\",\"children\":[]}]}]},{\"name\":\"EndorsementBox\",\"type\":\"string\",\"quantity\":\"1..1\",\"default\":\"\",\"description\":\"EI 栏：EI 栏。签注信息。这里的信息是endorsements 去重后的文本信息，并且加上了 nonRefAmount 的值\",\"children\":[]},{\"name\":\"Endorsements\",\"type\":\"array\",\"quantity\":\"0..1\",\"default\":\"\",\"description\":\"\",\"children\":[{\"name\":\"Carrier\",\"type\":\"object\",\"quantity\":\"1\",\"default\":\"\",\"description\":\"航空公司（承运人）两字码\",\"children\":[]},{\"name\":\"Text\",\"type\":\"string\",\"quantity\":\"1\",\"default\":\"\",\"description\":\"签注信息\",\"children\":[]}]},{\"name\":\"Waivers\",\"type\":\"object\",\"quantity\":\"1\",\"default\":\"\",\"description\":\"换开时适用的豁免\",\"children\":[{\"name\":\"Waiver\",\"type\":\"string\",\"quantity\":\"1..16\",\"default\":\"\",\"description\":\"豁免信息\",\"children\":[]}]}]}]}]},{\"name\":\"ItineraryOffers\",\"type\":\"object\",\"quantity\":\"0..1\",\"default\":\"\",\"description\":\"\",\"children\":[{\"name\":\"ItineraryOffer\",\"type\":\"object\",\"quantity\":\"1..n\",\"default\":\"\",\"description\":\"\",\"children\":[{\"name\":\"SellerId\",\"type\":\"string\",\"quantity\":\"1\",\"default\":\"\",\"description\":\"\",\"children\":[]},{\"name\":\"Ora\",\"type\":\"string\",\"quantity\":\"1\",\"default\":\"\",\"description\":\"出票航空公司：航空公司两字码 注：最后有一空格\",\"children\":[]},{\"name\":\"ItineraryFlights\",\"type\":\"object\",\"quantity\":\"1\",\"default\":\"\",\"description\":\"\",\"children\":[{\"name\":\"FlightId\",\"type\":\"string\",\"quantity\":\"1..16\",\"default\":\"\",\"description\":\"\",\"children\":[]}]},{\"name\":\"TotalFlightTime\",\"type\":\"string\",\"quantity\":\"1\",\"default\":\"\",\"description\":\"完整行程总的飞行时间：不包含地面时间，单位是“分钟”\",\"children\":[]},{\"name\":\"NumberOfOvernights\",\"type\":\"string\",\"quantity\":\"1\",\"default\":\"\",\"description\":\"跨天次数：如果没有跨天值为“0”\",\"children\":[]},{\"name\":\"Passengers\",\"type\":\"object\",\"quantity\":\"1\",\"default\":\"\",\"description\":\"\",\"children\":[{\"name\":\"Passenger\",\"type\":\"object\",\"quantity\":\"1\",\"default\":\"\",\"description\":\"旅客的唯一ID，和dataLibrary的passengers/id对应\",\"children\":[{\"name\":\"PassengerId\",\"type\":\"string\",\"quantity\":\"1\",\"default\":\"\",\"description\":\"\",\"children\":[]},{\"name\":\"ItineraryPricing\",\"type\":\"object\",\"quantity\":\"1\",\"default\":\"\",\"description\":\"\",\"children\":[{\"name\":\"FaresToFlightsMapping\",\"type\":\"object\",\"quantity\":\"1\",\"default\":\"\",\"description\":\"\",\"children\":[{\"name\":\"FareId\",\"type\":\"string\",\"quantity\":\"1\",\"default\":\"\",\"description\":\"\",\"children\":[]},{\"name\":\"CoveredFlights\",\"type\":\"object\",\"quantity\":\"1\",\"default\":\"\",\"description\":\"\",\"children\":[{\"name\":\"Id\",\"type\":\"string\",\"quantity\":\"1..16\",\"default\":\"\",\"description\":\"\",\"children\":[]}]}]},{\"name\":\"TicketingInfos\",\"type\":\"object\",\"quantity\":\"1\",\"default\":\"\",\"description\":\"\",\"children\":[{\"name\":\"TicketingInfo\",\"type\":\"object\",\"quantity\":\"1..n\",\"default\":\"\",\"description\":\"\",\"children\":[{\"name\":\"TicketMaskId\",\"type\":\"string\",\"quantity\":\"1\",\"default\":\"\",\"description\":\"该旅客票的唯一 ID。同 dataLibrary 的 TicketMask/id。\",\"children\":[]},{\"name\":\"CoveredFlights\",\"type\":\"object\",\"quantity\":\"1\",\"default\":\"\",\"description\":\"\",\"children\":[{\"name\":\"Id\",\"type\":\"string\",\"quantity\":\"1..16\",\"default\":\"\",\"description\":\"\",\"children\":[]}]},{\"name\":\"BaseFareDiff\",\"type\":\"object\",\"quantity\":\"1\",\"default\":\"\",\"description\":\"票面差价（同原票支付 货币）：票面差价（同原票支付货币）\",\"children\":[{\"name\":\"Amount\",\"type\":\"string\",\"quantity\":\"1..1\",\"default\":\"\",\"description\":\"金额：金额\",\"children\":[]},{\"name\":\"Currency\",\"type\":\"object\",\"quantity\":\"1..1\",\"default\":\"\",\"description\":\"货币：货币（同新票支付货币）\",\"children\":[]}]},{\"name\":\"RepriceFareDiff\",\"type\":\"object\",\"quantity\":\"1\",\"default\":\"\",\"description\":\"票面差价（同换开支付 货币）：票面差价（同换开支付货币）\",\"children\":[{\"name\":\"Amount\",\"type\":\"string\",\"quantity\":\"1..1\",\"default\":\"\",\"description\":\"金额：金额\",\"children\":[]},{\"name\":\"Currency\",\"type\":\"object\",\"quantity\":\"1..1\",\"default\":\"\",\"description\":\"货币：货币（同新票支付货币）\",\"children\":[]}]},{\"name\":\"TaxDiff\",\"type\":\"object\",\"quantity\":\"1\",\"default\":\"\",\"description\":\"税的差价（同新票支付 货币）：税的差价（同新票支付货币）\",\"children\":[{\"name\":\"Amount\",\"type\":\"string\",\"quantity\":\"1..1\",\"default\":\"\",\"description\":\"金额：金额\",\"children\":[]},{\"name\":\"Currency\",\"type\":\"object\",\"quantity\":\"1..1\",\"default\":\"\",\"description\":\"货币：货币（同新票支付货币）\",\"children\":[]}]},{\"name\":\"ServiceFee\",\"type\":\"object\",\"quantity\":\"1\",\"default\":\"\",\"description\":\"变更手续费（同新票支 付货币）：变更手续费（同新票支付货币）\",\"children\":[{\"name\":\"Amount\",\"type\":\"string\",\"quantity\":\"1..1\",\"default\":\"\",\"description\":\"金额：金额\",\"children\":[]},{\"name\":\"Currency\",\"type\":\"object\",\"quantity\":\"1..1\",\"default\":\"\",\"description\":\"货币：货币（同新票支付货币）\",\"children\":[]}]},{\"name\":\"TotalFare\",\"type\":\"object\",\"quantity\":\"1\",\"default\":\"\",\"description\":\"\",\"children\":[{\"name\":\"Amount\",\"type\":\"string\",\"quantity\":\"1..1\",\"default\":\"\",\"description\":\"金额：金额\",\"children\":[]},{\"name\":\"Currency\",\"type\":\"object\",\"quantity\":\"1..1\",\"default\":\"\",\"description\":\"货币：货币（同新票支付货币）\",\"children\":[]}]},{\"name\":\"RepriceSummary\",\"type\":\"object\",\"quantity\":\"1\",\"default\":\"\",\"description\":\"换开币种换开总结（新 票货币）：换开币种换开总结（新票货币）\",\"children\":[{\"name\":\"BaseFare\",\"type\":\"object\",\"quantity\":\"1\",\"default\":\"\",\"description\":\"\",\"children\":[{\"name\":\"Amount\",\"type\":\"string\",\"quantity\":\"1..1\",\"default\":\"\",\"description\":\"金额：金额\",\"children\":[]},{\"name\":\"Currency\",\"type\":\"object\",\"quantity\":\"1..1\",\"default\":\"\",\"description\":\"货币：货币（同新票支付货币）\",\"children\":[]}]},{\"name\":\"EquivalentFare\",\"type\":\"object\",\"quantity\":\"1\",\"default\":\"\",\"description\":\"\",\"children\":[{\"name\":\"Amount\",\"type\":\"string\",\"quantity\":\"1..1\",\"default\":\"\",\"description\":\"金额：金额\",\"children\":[]},{\"name\":\"Currency\",\"type\":\"object\",\"quantity\":\"1..1\",\"default\":\"\",\"description\":\"货币：货币（同新票支付货币）\",\"children\":[]}]},{\"name\":\"SalesFare\",\"type\":\"object\",\"quantity\":\"1\",\"default\":\"\",\"description\":\"新票实付价格\",\"children\":[{\"name\":\"Amount\",\"type\":\"string\",\"quantity\":\"1..1\",\"default\":\"\",\"description\":\"金额：金额\",\"children\":[]},{\"name\":\"Currency\",\"type\":\"object\",\"quantity\":\"1..1\",\"default\":\"\",\"description\":\"货币：货币（同新票支付货币）\",\"children\":[]}]},{\"name\":\"PenaltyTaxes\",\"type\":\"object\",\"quantity\":\"1\",\"default\":\"\",\"description\":\"罚金的税（是国家税的 一种）：罚金的税（是国家税的一种）\",\"children\":[{\"name\":\"Id\",\"type\":\"string\",\"quantity\":\"1\",\"default\":\"\",\"description\":\"税的ID号,dataLibrary-Taxes中的id\",\"children\":[]}]},{\"name\":\"TaxUsage\",\"type\":\"object\",\"quantity\":\"1\",\"default\":\"\",\"description\":\"新旧票所有的税按照“REFUNDED/NEW/USED\\\" 分类：新旧票所有的税按照 “REFUNDED/NEW/USED\\\"分类\",\"children\":[{\"name\":\"TaxCode\",\"type\":\"string\",\"quantity\":\"1\",\"default\":\"\",\"description\":\"税代码：税代码\",\"children\":[]},{\"name\":\"Airport\",\"type\":\"object\",\"quantity\":\"1\",\"default\":\"\",\"description\":\"机场：ZP 和 XF 税时，对应机场信息\",\"children\":[]},{\"name\":\"Price\",\"type\":\"object\",\"quantity\":\"1\",\"default\":\"\",\"description\":\"\",\"children\":[{\"name\":\"Amount\",\"type\":\"string\",\"quantity\":\"1..1\",\"default\":\"\",\"description\":\"金额：金额\",\"children\":[]},{\"name\":\"Currency\",\"type\":\"object\",\"quantity\":\"1..1\",\"default\":\"\",\"description\":\"货币：货币（同新票支付货币）\",\"children\":[]}]},{\"name\":\"Usage\",\"type\":\"string\",\"quantity\":\"1\",\"default\":\"\",\"description\":\"税的类型\",\"children\":[]}]}]}]}]}]}]}]}]}]}]}]",
    "errorCodes": "[{\"code\":\" 403 \",\"name\":null,\"msg\":null,\"msgZh\":\" 用户名、密码、IP错误或无权限 \"},{\"code\":\" -402 \",\"name\":null,\"msg\":\" INPUT_ERROR \",\"msgZh\":\" 格式输入错误 \"},{\"code\":\" -390 \",\"name\":null,\"msg\":\" IBESERVICE_ERROR \",\"msgZh\":\" IBE服务异常 \"},{\"code\":\" -61701 \",\"name\":null,\"msg\":\" Ticket and order info not match! \",\"msgZh\":\" 票号和订单号不匹配 \"},{\"code\":\" -308 \",\"name\":null,\"msg\":\" ORDER_NOT_PERMITTED \",\"msgZh\":\" 订单无权限（订单号错误） \"},{\"code\":\" -55400 \",\"name\":null,\"msg\":\" imported tickets, cannot perform the operation. \",\"msgZh\":\" 客票为线下导入，无法执行该操作。 \"},{\"code\":\" -400 \",\"name\":null,\"msg\":\" format of xml String is not valid \",\"msgZh\":\" xml内容格式错误 \"},{\"code\":\" -402 \",\"name\":null,\"msg\":\" input error \",\"msgZh\":\" 输入错误 \"}]",
    "createTime": "2025-07-08T15:15:00.000+08:00",
    "createUser": "xyi",
    "updateTime": "2025-12-03T11:10:49.000+08:00",
    "updateUser": "zjhe",
    "qaApiDemos": [
      {
        "id": "22257378611167951",
        "apiDocId": 17089797243798047,
        "seqNumber": 1,
        "demoDesc": "成功.xml",
        "request": "<?xml version=\"1.0\" encoding=\"UTF-8\"?>\n<TRR_VoluntaryReshopRQ>\n\t<BookingOrderID>200807093355d9eb473</BookingOrderID>\n\t<TicketInfo>\n\t\t<TicketNo>781-3710399242</TicketNo>\n\t\t<PassengerName>ZHOU/XIA</PassengerName>\n\t\t<ValidatingCarrier>MU</ValidatingCarrier>\n\t</TicketInfo>\n\t<POS>\n\t\t<HostCode>1E</HostCode>\n\t\t<TicketingCity>PEK</TicketingCity>\n\t\t<DepartmentCode>\n\t\t</DepartmentCode>\n\t\t<OfficeCode>BJS191</OfficeCode>\n\t\t<IataCode>99999992</IataCode>\n\t</POS>\n\t<Segments>\n\t\t<Segment>\n\t\t\t<FlightId>1</FlightId>\n\t\t\t<MarketingCarrier>MU</MarketingCarrier>\n\t\t\t<FlightNo>8661</FlightNo>\n\t\t\t<CabinCode>Y</CabinCode>\n\t\t\t<DepartureDateTime>2020-10-17T23:20:00</DepartureDateTime>\n\t\t\t<Equipment>77W</Equipment>\n\t\t\t<ArrivalDateTime>2020-10-18T05:50:00</ArrivalDateTime>\n\t\t\t<DepartureCity>PVG</DepartureCity>\n\t\t\t<ArrivalCity>CDG</ArrivalCity>\n\t\t\t<StopoverOrTransfer>X</StopoverOrTransfer>\n\t\t\t<NumberOfStops>0</NumberOfStops>\n\t\t\t<BookingStatus>OK</BookingStatus>\n\t\t</Segment>\n\t</Segments>\n\t<NewSegments>\n\t\t<NewSegment>\n\t\t\t<Origin>\n\t\t\t\t<Name>PVG</Name>\n\t\t\t\t<Type>AIRPORT</Type>\n\t\t\t</Origin>\n\t\t\t<Destination>\n\t\t\t\t<Name>CDG</Name>\n\t\t\t\t<Type>AIRPORT</Type>\n\t\t\t</Destination>\n\t\t\t<DepartDate>2020-11-10</DepartDate>\n\t\t\t<CoveredSegments>\n\t\t\t\t<FlightId>1</FlightId>\n\t\t\t</CoveredSegments>\n\t\t</NewSegment>\n\t</NewSegments>\n</TRR_VoluntaryReshopRQ>",
        "response": null,
        "createTime": "2025-09-03T16:11:30.000+08:00",
        "createUser": "jiangdequan",
        "updateTime": null,
        "updateUser": null
      }
    ],
    "url": "/xml/AirIntlReShopOrder"
  }
}